{
	"type": "FeatureCollection",
	"features": [
		{
			"geometry": { "coordinates": [37.5585388370174, 55.8833567078318], "type": "Point" },
			"properties": {
				"": "32",
				"AdmArea": "Северный административный округ",
				"District": "Восточное Дегунино",
				"Address": "город Москва, Дубнинская улица, дом 32",
				"PropertyType": "помещение",
				"ObjectArea": 663.3,
				"Note": "",
				"global_id": "832170569"
			},
			"type": "Feature"
		},
		{
			"geometry": { "coordinates": [37.7356539965817, 55.6104028057292], "type": "Point" },
			"properties": {
				"": "51",
				"AdmArea": "Южный административный округ",
				"District": "Орехово-Борисово Южное",
				"Address": "город Москва, Воронежская улица, дом 24, корпус 1",
				"PropertyType": "помещение",
				"ObjectArea": 789.9,
				"Note": "",
				"global_id": "831255560"
			},
			"type": "Feature"
		},
		{
			"geometry": { "coordinates": [37.8330683328914, 55.7511853611767], "type": "Point" },
			"properties": {
				"": "511",
				"AdmArea": "Восточный административный округ",
				"District": "Ивановское",
				"Address": "город Москва, улица Молостовых, дом 19, корпус 1",
				"PropertyType": "помещение",
				"ObjectArea": 650.2,
				"Note": "",
				"global_id": "901650587"
			},
			"type": "Feature"
		},
		{
			"geometry": { "coordinates": [37.5362905295167, 55.8818509316168], "type": "Point" },
			"properties": {
				"": "671",
				"AdmArea": "Северный административный округ",
				"District": "Дмитровский",
				"Address": "город Москва, Учинская улица, дом 1",
				"PropertyType": "помещение",
				"ObjectArea": 618.6,
				"Note": "",
				"global_id": "909024811"
			},
			"type": "Feature"
		},
		{
			"geometry": { "coordinates": [37.40452166546, 55.8137847869587], "type": "Point" },
			"properties": {
				"": "947",
				"AdmArea": "Северо-Западный административный округ",
				"District": "Строгино",
				"Address": "город Москва, улица Кулакова, дом 3, корпус 2",
				"PropertyType": "помещение",
				"ObjectArea": 1033.7,
				"Note": "-",
				"global_id": "1016281807"
			},
			"type": "Feature"
		}
	]
}
